counter-1/top.v
module top(
    input clk,
    input rst,
    output reg [2:0] f
);
    always_ff @(posedge clk) begin
        if (!rst) begin
            f <= 0;
        end else begin
            f <= f + 1;
        end
    end
endmodule

adder-1/waveform.vcd
$version Generated by VerilatedVcd $end
$date Fri Aug  8 22:41:18 2025
 $end
$timescale   1ps $end

 $scope module TOP $end
  $var wire  1 # clk $end
  $var wire  3 % f [2:0] $end
  $var wire  1 $ rst $end
  $scope module top $end
   $var wire  1 # clk $end
   $var wire  3 % f [2:0] $end
   $var wire  1 $ rst $end
  $upscope $end
 $upscope $end
$enddefinitions $end


#0
1#
1$
b000 %
#1
0#
#2
1#
b001 %
#3
0#
#4
1#
b010 %
#5
0#
#6
1#
b011 %
#7
0#
#8
1#
b100 %
#9
0#
#10
1#
b101 %
#11
0#
#12
1#
b110 %
#13
0#
#14
1#
b111 %
#15
0#
#16
1#
b000 %
#17
0#
#18
1#
b001 %
#19
0#
#20
1#
b010 %
#21
0#
#22
1#
b011 %
#23
0#
#24
1#
b100 %
#25
0#
#26
1#
b101 %
#27
0#
#28
1#
b110 %
#29
0#
#30
1#
b111 %
#31
0#
#32
1#
b000 %
#33
0#
#34
1#
b001 %
#35
0#
#36
1#
b010 %
#37
0#
#38
1#
b011 %
#39
0#
#40
1#
b100 %
#41
0#
#42
1#
b101 %
#43
0#
#44
1#
b110 %
#45
0#
#46
1#
b111 %
#47
0#
#48
1#
b000 %
#49
0#
#50
1#
b001 %
#51
0#
#52
1#
b010 %
#53
0#
#54
1#
b011 %
#55
0#
#56
1#
b100 %
#57
0#
#58
1#
b101 %
#59
0#
#60
1#
b110 %
#61
0#
#62
1#
b111 %
#63
0#
#64
1#
b000 %
#65
0#
#66
1#
b001 %
#67
0#
#68
1#
b010 %
#69
0#
#70
1#
b011 %
#71
0#
#72
1#
b100 %
#73
0#
#74
1#
b101 %
#75
0#
#76
1#
b110 %
#77
0#
#78
1#
b111 %
#79
0#
#80
1#
b000 %
#81
0#
#82
1#
b001 %
#83
0#
#84
1#
b010 %
#85
0#
#86
1#
b011 %
#87
0#
#88
1#
b100 %
#89
0#
#90
1#
b101 %
#91
0#
#92
1#
b110 %
#93
0#
#94
1#
b111 %
#95
0#
#96
1#
b000 %
#97
0#
#98
1#
b001 %
#99
0#
#100
1#
b010 %
#101
0#
#102
1#
b011 %
#103
0#
#104
1#
b100 %
#105
0#
#106
1#
b101 %
#107
0#
#108
1#
b110 %
#109
0#
#110
1#
b111 %
#111
0#
#112
1#
b000 %
#113
0#
#114
1#
b001 %
#115
0#
#116
1#
b010 %
#117
0#
#118
1#
b011 %
#119
0#
#120
1#
b100 %
#121
0#
#122
1#
b101 %
#123
0#
#124
1#
b110 %
#125
0#
#126
1#
b111 %
#127
0#
#128
1#
b000 %
#129
0#
#130
1#
b001 %
#131
0#
#132
1#
b010 %
#133
0#
#134
1#
b011 %
#135
0#
#136
1#
b100 %
#137
0#
#138
1#
b101 %
#139
0#
#140
1#
b110 %
#141
0#
#142
1#
b111 %
#143
0#
#144
1#
b000 %
#145
0#
#146
1#
b001 %
#147
0#
#148
1#
b010 %
#149
0#
#150
1#
b011 %
#151
0#
#152
1#
b100 %
#153
0#
#154
1#
b101 %
#155
0#
#156
1#
b110 %
#157
0#
#158
1#
b111 %
#159
0#
#160
1#
b000 %
#161
0#
#162
1#
b001 %
#163
0#
#164
1#
b010 %
#165
0#
#166
1#
b011 %
#167
0#
#168
1#
b100 %
#169
0#
#170
1#
b101 %
#171
0#
#172
1#
b110 %
#173
0#
#174
1#
b111 %
#175
0#
#176
1#
b000 %
#177
0#
#178
1#
b001 %
#179
0#
#180
1#
b010 %
#181
0#
#182
1#
b011 %
#183
0#
#184
1#
b100 %
#185
0#
#186
1#
b101 %
#187
0#
#188
1#
b110 %
#189
0#
#190
1#
b111 %
#191
0#
#192
1#
b000 %
#193
0#
#194
1#
b001 %
#195
0#
#196
1#
b010 %
#197
0#
#198
1#
b011 %
#199
0#
#200
1#
b100 %
#201
0#
#202
1#
b101 %
#203
0#
#204
1#
b110 %
#205
0#
#206
1#
b111 %
#207
0#
#208
1#
b000 %
#209
0#
#210
1#
b001 %
#211
0#
#212
1#
b010 %
#213
0#
#214
1#
b011 %
#215
0#
#216
1#
b100 %
#217
0#
#218
1#
b101 %
#219
0#
#220
1#
b110 %
#221
0#
#222
1#
b111 %
#223
0#
#224
1#
b000 %
#225
0#
#226
1#
b001 %
#227
0#
#228
1#
b010 %
#229
0#
#230
1#
b011 %
#231
0#
#232
1#
b100 %
#233
0#
#234
1#
b101 %
#235
0#
#236
1#
b110 %
#237
0#
#238
1#
b111 %
#239
0#
#240
1#
b000 %
#241
0#
#242
1#
b001 %
#243
0#
#244
1#
b010 %
#245
0#
#246
1#
b011 %
#247
0#
#248
1#
b100 %
#249
0#
#250
1#
b101 %
#251
0#
#252
1#
b110 %
#253
0#
#254
1#
b111 %
#255
0#
#256
1#
b000 %
#257
0#
#258
1#
b001 %
#259
0#
#260
1#
b010 %
#261
0#
#262
1#
b011 %
#263
0#
#264
1#
b100 %
#265
0#
#266
1#
b101 %
#267
0#
#268
1#
b110 %
#269
0#
#270
1#
b111 %
#271
0#
#272
1#
b000 %
#273
0#
#274
1#
b001 %
#275
0#
#276
1#
b010 %
#277
0#
#278
1#
b011 %
#279
0#
#280
1#
b100 %
#281
0#
#282
1#
b101 %
#283
0#
#284
1#
b110 %
#285
0#
#286
1#
b111 %
#287
0#
#288
1#
b000 %
#289
0#
#290
1#
b001 %
#291
0#
#292
1#
b010 %
#293
0#
#294
1#
b011 %
#295
0#
#296
1#
b100 %
#297
0#
#298
1#
b101 %
#299
0#
#300
1#
b110 %
#301
0#
#302
1#
b111 %
#303
0#
#304
1#
b000 %
#305
0#
#306
1#
b001 %
#307
0#
#308
1#
b010 %
#309
0#
#310
1#
b011 %
#311
0#
#312
1#
b100 %
#313
0#
#314
1#
b101 %
#315
0#
#316
1#
b110 %
#317
0#
#318
1#
b111 %
#319
0#
#320
1#
b000 %
#321
0#
#322
1#
b001 %
#323
0#
#324
1#
b010 %
#325
0#
#326
1#
b011 %
#327
0#
#328
1#
b100 %
#329
0#
#330
1#
b101 %
#331
0#
#332
1#
b110 %
#333
0#
#334
1#
b111 %
#335
0#
#336
1#
b000 %
#337
0#
#338
1#
b001 %
#339
0#
#340
1#
b010 %
#341
0#
#342
1#
b011 %
#343
0#
#344
1#
b100 %
#345
0#
#346
1#
b101 %
#347
0#
#348
1#
b110 %
#349
0#
#350
1#
b111 %
#351
0#
#352
1#
b000 %
#353
0#
#354
1#
b001 %
#355
0#
#356
1#
b010 %
#357
0#
#358
1#
b011 %
#359
0#
#360
1#
b100 %
#361
0#
#362
1#
b101 %
#363
0#
#364
1#
b110 %
#365
0#
#366
1#
b111 %
#367
0#
#368
1#
b000 %
#369
0#
#370
1#
b001 %
#371
0#
#372
1#
b010 %
#373
0#
#374
1#
b011 %
#375
0#
#376
1#
b100 %
#377
0#
#378
1#
b101 %
#379
0#
#380
1#
b110 %
#381
0#
#382
1#
b111 %
#383
0#
#384
1#
b000 %
#385
0#
#386
1#
b001 %
#387
0#
#388
1#
b010 %
#389
0#
#390
1#
b011 %
#391
0#
#392
1#
b100 %
#393
0#
#394
1#
b101 %
#395
0#
#396
1#
b110 %
#397
0#
#398
1#
b111 %
#399
0#
#400
1#
b000 %
#401
0#
#402
1#
b001 %
#403
0#
#404
1#
b010 %
#405
0#
#406
1#
b011 %
#407
0#
#408
1#
b100 %
#409
0#
#410
1#
b101 %
#411
0#
#412
1#
b110 %
#413
0#
#414
1#
b111 %
#415
0#
#416
1#
b000 %
#417
0#
#418
1#
b001 %
#419
0#
#420
1#
b010 %
#421
0#
#422
1#
b011 %
#423
0#
#424
1#
b100 %
#425
0#
#426
1#
b101 %
#427
0#
#428
1#
b110 %
#429
0#
#430
1#
b111 %
#431
0#
#432
1#
b000 %
#433
0#
#434
1#
b001 %
#435
0#
#436
1#
b010 %
#437
0#
#438
1#
b011 %
#439
0#
#440
1#
b100 %
#441
0#
#442
1#
b101 %
#443
0#
#444
1#
b110 %
#445
0#
#446
1#
b111 %
#447
0#
#448
1#
b000 %
#449
0#
#450
1#
b001 %
#451
0#
#452
1#
b010 %
#453
0#
#454
1#
b011 %
#455
0#
#456
1#
b100 %
#457
0#
#458
1#
b101 %
#459
0#
#460
1#
b110 %
#461
0#
#462
1#
b111 %
#463
0#
#464
1#
b000 %
#465
0#
#466
1#
b001 %
#467
0#
#468
1#
b010 %
#469
0#
#470
1#
b011 %
#471
0#
#472
1#
b100 %
#473
0#
#474
1#
b101 %
#475
0#
#476
1#
b110 %
#477
0#
#478
1#
b111 %
#479
0#
#480
1#
b000 %
#481
0#
#482
1#
b001 %
#483
0#
#484
1#
b010 %
#485
0#
#486
1#
b011 %
#487
0#
#488
1#
b100 %
#489
0#
#490
1#
b101 %
#491
0#
#492
1#
b110 %
#493
0#
#494
1#
b111 %
#495
0#
#496
1#
b000 %
#497
0#
#498
1#
b001 %
#499
0#
#500
1#
b010 %
#501
0#
#502
1#
b011 %
#503
0#
#504
1#
b100 %
#505
0#
#506
1#
b101 %
#507
0#
#508
1#
b110 %
#509
0#
#510
1#
b111 %
#511
0#
#512
1#
b000 %
#513
0#
#514
1#
b001 %
#515
0#
#516
1#
b010 %
#517
0#
#518
1#
b011 %
#519
0#
#520
1#
b100 %
#521
0#
#522
1#
b101 %
#523
0#
#524
1#
b110 %
#525
0#
#526
1#
b111 %
#527
0#
#528
1#
b000 %
#529
0#
#530
1#
b001 %
#531
0#
#532
1#
b010 %
#533
0#
#534
1#
b011 %
#535
0#
#536
1#
b100 %
#537
0#
#538
1#
b101 %
#539
0#
#540
1#
b110 %
#541
0#
#542
1#
b111 %
#543
0#
#544
1#
b000 %
#545
0#
#546
1#
b001 %
#547
0#
#548
1#
b010 %
#549
0#
#550
1#
b011 %
#551
0#
#552
1#
b100 %
#553
0#
#554
1#
b101 %
#555
0#
#556
1#
b110 %
#557
0#
#558
1#
b111 %
#559
0#
#560
1#
b000 %
#561
0#
#562
1#
b001 %
#563
0#
#564
1#
b010 %
#565
0#
#566
1#
b011 %
#567
0#
#568
1#
b100 %
#569
0#
#570
1#
b101 %
#571
0#
#572
1#
b110 %
#573
0#
#574
1#
b111 %
#575
0#
#576
1#
b000 %
#577
0#
#578
1#
b001 %
#579
0#
#580
1#
b010 %
#581
0#
#582
1#
b011 %
#583
0#
#584
1#
b100 %
#585
0#
#586
1#
b101 %
#587
0#
#588
1#
b110 %
#589
0#
#590
1#
b111 %
#591
0#
#592
1#
b000 %
#593
0#
#594
1#
b001 %
#595
0#
#596
1#
b010 %
#597
0#
#598
1#
b011 %
#599
0#
#600
1#
b100 %
#601
0#
#602
1#
b101 %
#603
0#
#604
1#
b110 %
#605
0#
#606
1#
b111 %
#607
0#
#608
1#
b000 %
#609
0#
#610
1#
b001 %
#611
0#
#612
1#
b010 %
#613
0#
#614
1#
b011 %
#615
0#
#616
1#
b100 %
#617
0#
#618
1#
b101 %
#619
0#
#620
1#
b110 %
#621
0#
#622
1#
b111 %
#623
0#
#624
1#
b000 %
#625
0#
#626
1#
b001 %
#627
0#
#628
1#
b010 %
#629
0#
#630
1#
b011 %
#631
0#
#632
1#
b100 %
#633
0#
#634
1#
b101 %
#635
0#
#636
1#
b110 %
#637
0#
#638
1#
b111 %
#639
0#
#640
1#
b000 %
#641
0#
#642
1#
b001 %
#643
0#
#644
1#
b010 %
#645
0#
#646
1#
b011 %
#647
0#
#648
1#
b100 %
#649
0#
#650
1#
b101 %
#651
0#
#652
1#
b110 %
#653
0#
#654
1#
b111 %
#655
0#
#656
1#
b000 %
#657
0#
#658
1#
b001 %
#659
0#
#660
1#
b010 %
#661
0#
#662
1#
b011 %
#663
0#
#664
1#
b100 %
#665
0#
#666
1#
b101 %
#667
0#
#668
1#
b110 %
#669
0#
#670
1#
b111 %
#671
0#
#672
1#
b000 %
#673
0#
#674
1#
b001 %
#675
0#
#676
1#
b010 %
#677
0#
#678
1#
b011 %
#679
0#
#680
1#
b100 %
#681
0#
#682
1#
b101 %
#683
0#
#684
1#
b110 %
#685
0#
#686
1#
b111 %
#687
0#
#688
1#
b000 %
#689
0#
#690
1#
b001 %
#691
0#
#692
1#
b010 %
#693
0#
#694
1#
b011 %
#695
0#
#696
1#
b100 %
#697
0#
#698
1#
b101 %
#699
0#
#700
1#
b110 %
#701
0#
#702
1#
b111 %
#703
0#
#704
1#
b000 %
#705
0#
#706
1#
b001 %
#707
0#
#708
1#
b010 %
#709
0#
#710
1#
b011 %
#711
0#
#712
1#
b100 %
#713
0#
#714
1#
b101 %
#715
0#
#716
1#
b110 %
#717
0#
#718
1#
b111 %
#719
0#
#720
1#
b000 %
#721
0#
#722
1#
b001 %
#723
0#
#724
1#
b010 %
#725
0#
#726
1#
b011 %
#727
0#
#728
1#
b100 %
#729
0#
#730
1#
b101 %
#731
0#
#732
1#
b110 %
#733
0#
#734
1#
b111 %
#735
0#
#736
1#
b000 %
#737
0#
#738
1#
b001 %
#739
0#
#740
1#
b010 %
#741
0#
#742
1#
b011 %
#743
0#
#744
1#
b100 %
#745
0#
#746
1#
b101 %
#747
0#
#748
1#
b110 %
#749
0#
#750
1#
b111 %
#751
0#
#752
1#
b000 %
#753
0#
#754
1#
b001 %
#755
0#
#756
1#
b010 %
#757
0#
#758
1#
b011 %
#759
0#
#760
1#
b100 %
#761
0#
#762
1#
b101 %
#763
0#
#764
1#
b110 %
#765
0#
#766
1#
b111 %
#767
0#
#768
1#
b000 %
#769
0#
#770
1#
b001 %
#771
0#
#772
1#
b010 %
#773
0#
#774
1#
b011 %
#775
0#
#776
1#
b100 %
#777
0#
#778
1#
b101 %
#779
0#
#780
1#
b110 %
#781
0#
#782
1#
b111 %
#783
0#
#784
1#
b000 %
#785
0#
#786
1#
b001 %
#787
0#
#788
1#
b010 %
#789
0#
#790
1#
b011 %
#791
0#
#792
1#
b100 %
#793
0#
#794
1#
b101 %
#795
0#
#796
1#
b110 %
#797
0#
#798
1#
b111 %
