quickstart-1/top.v
module top(
  input clk,
  input rst,
  output reg [9:0]f
);  

  always @(posedge clk) begin
    if (!rst)
      f <= 0;
    else
      f <= f+1;
  end

endmodule

quickstart-1/waveform.vcd
$version Generated by VerilatedVcd $end
$date Wed Aug  6 15:27:04 2025
 $end
$timescale   1ps $end

 $scope module TOP $end
  $var wire  1 # clk $end
  $var wire 10 % f [9:0] $end
  $var wire  1 $ rst $end
  $scope module top $end
   $var wire  1 # clk $end
   $var wire 10 % f [9:0] $end
   $var wire  1 $ rst $end
  $upscope $end
 $upscope $end
$enddefinitions $end


#0
1#
1$
b0000000000 %
#1
0#
#2
1#
b0000000001 %
#3
0#
#4
1#
b0000000010 %
#5
0#
#6
1#
b0000000011 %
#7
0#
#8
1#
b0000000100 %
#9
0#
#10
1#
b0000000101 %
#11
0#
#12
1#
b0000000110 %
#13
0#
#14
1#
b0000000111 %
#15
0#
#16
1#
b0000001000 %
#17
0#
#18
1#
b0000001001 %
#19
0#
#20
1#
b0000001010 %
#21
0#
#22
1#
b0000001011 %
#23
0#
#24
1#
b0000001100 %
#25
0#
#26
1#
b0000001101 %
#27
0#
#28
1#
b0000001110 %
#29
0#
#30
1#
b0000001111 %
#31
0#
#32
1#
b0000010000 %
#33
0#
#34
1#
b0000010001 %
#35
0#
#36
1#
b0000010010 %
#37
0#
#38
1#
b0000010011 %
#39
0#
#40
1#
b0000010100 %
#41
0#
#42
1#
b0000010101 %
#43
0#
#44
1#
b0000010110 %
#45
0#
#46
1#
b0000010111 %
#47
0#
#48
1#
b0000011000 %
#49
0#
#50
1#
b0000011001 %
#51
0#
#52
1#
b0000011010 %
#53
0#
#54
1#
b0000011011 %
#55
0#
#56
1#
b0000011100 %
#57
0#
#58
1#
b0000011101 %
#59
0#
#60
1#
b0000011110 %
#61
0#
#62
1#
b0000011111 %
#63
0#
#64
1#
b0000100000 %
#65
0#
#66
1#
b0000100001 %
#67
0#
#68
1#
b0000100010 %
#69
0#
#70
1#
b0000100011 %
#71
0#
#72
1#
b0000100100 %
#73
0#
#74
1#
b0000100101 %
#75
0#
#76
1#
b0000100110 %
#77
0#
#78
1#
b0000100111 %
#79
0#
#80
1#
b0000101000 %
#81
0#
#82
1#
b0000101001 %
#83
0#
#84
1#
b0000101010 %
#85
0#
#86
1#
b0000101011 %
#87
0#
#88
1#
b0000101100 %
#89
0#
#90
1#
b0000101101 %
#91
0#
#92
1#
b0000101110 %
#93
0#
#94
1#
b0000101111 %
#95
0#
#96
1#
b0000110000 %
#97
0#
#98
1#
b0000110001 %
#99
0#
#100
1#
b0000110010 %
#101
0#
#102
1#
b0000110011 %
#103
0#
#104
1#
b0000110100 %
#105
0#
#106
1#
b0000110101 %
#107
0#
#108
1#
b0000110110 %
#109
0#
#110
1#
b0000110111 %
#111
0#
#112
1#
b0000111000 %
#113
0#
#114
1#
b0000111001 %
#115
0#
#116
1#
b0000111010 %
#117
0#
#118
1#
b0000111011 %
#119
0#
#120
1#
b0000111100 %
#121
0#
#122
1#
b0000111101 %
#123
0#
#124
1#
b0000111110 %
#125
0#
#126
1#
b0000111111 %
#127
0#
#128
1#
b0001000000 %
#129
0#
#130
1#
b0001000001 %
#131
0#
#132
1#
b0001000010 %
#133
0#
#134
1#
b0001000011 %
#135
0#
#136
1#
b0001000100 %
#137
0#
#138
1#
b0001000101 %
#139
0#
#140
1#
b0001000110 %
#141
0#
#142
1#
b0001000111 %
#143
0#
#144
1#
b0001001000 %
#145
0#
#146
1#
b0001001001 %
#147
0#
#148
1#
b0001001010 %
#149
0#
#150
1#
b0001001011 %
#151
0#
#152
1#
b0001001100 %
#153
0#
#154
1#
b0001001101 %
#155
0#
#156
1#
b0001001110 %
#157
0#
#158
1#
b0001001111 %
#159
0#
#160
1#
b0001010000 %
#161
0#
#162
1#
b0001010001 %
#163
0#
#164
1#
b0001010010 %
#165
0#
#166
1#
b0001010011 %
#167
0#
#168
1#
b0001010100 %
#169
0#
#170
1#
b0001010101 %
#171
0#
#172
1#
b0001010110 %
#173
0#
#174
1#
b0001010111 %
#175
0#
#176
1#
b0001011000 %
#177
0#
#178
1#
b0001011001 %
#179
0#
#180
1#
b0001011010 %
#181
0#
#182
1#
b0001011011 %
#183
0#
#184
1#
b0001011100 %
#185
0#
#186
1#
b0001011101 %
#187
0#
#188
1#
b0001011110 %
#189
0#
#190
1#
b0001011111 %
#191
0#
#192
1#
b0001100000 %
#193
0#
#194
1#
b0001100001 %
#195
0#
#196
1#
b0001100010 %
#197
0#
#198
1#
b0001100011 %
